linelog/__init__.py
linelog/__main__.py
linelog/apputil.py
linelog/console.py
linelog/default_config.yaml
linelog/filetypes.json
linelog/log_util.py
linelog/plotter.py
linelog-1.0.3.dist-info/LICENSE.md
linelog-1.0.3.dist-info/METADATA
linelog-1.0.3.dist-info/WHEEL
linelog-1.0.3.dist-info/entry_points.txt
linelog-1.0.3.dist-info/RECORD
