Metadata-Version: 2.1
Name: linelog
Version: 1.0.3
Summary: Track your total lines of code committed in git, and view the trend over time via a simple TUI graph visualization
License: 0BSD
Author: keagud
Author-email: keagud@protonmail.com
Requires-Python: >=3.10,<4.0
Classifier: License :: Other/Proprietary License
Classifier: Programming Language :: Python :: 3
Classifier: Programming Language :: Python :: 3.10
Classifier: Programming Language :: Python :: 3.11
Requires-Dist: argparse (>=1.4.0,<2.0.0)
Requires-Dist: plotille (>=5.0.0,<6.0.0)
Requires-Dist: pygit2 (>=1.11.1,<2.0.0)
Requires-Dist: pyyaml (>=6.0,<7.0)
Requires-Dist: rich (>=13.3.1,<14.0.0)
Requires-Dist: toml (>=0.10.2,<0.11.0)
